moesif_gcp_function/__init__.py
moesif_gcp_function/client_ip.py
moesif_gcp_function/global_variable.py
moesif_gcp_function/middleware.py
moesif_gcp_function/update_companies.py
moesif_gcp_function/update_users.py
moesif_gcp_function-1.0.0.dist-info/licenses/LICENSE
moesif_gcp_function-1.0.0.dist-info/METADATA
moesif_gcp_function-1.0.0.dist-info/WHEEL
moesif_gcp_function-1.0.0.dist-info/top_level.txt
moesif_gcp_function-1.0.0.dist-info/RECORD
